dpckan/__init__.py
dpckan/cli.py
dpckan/create_dataset.py
dpckan/create_resource.py
dpckan/diff_dataset.py
dpckan/diff_resource.py
dpckan/functions.py
dpckan/get_dataset.py
dpckan/update_dataset.py
dpckan/update_resource.py
dpckan/validations.py
dpckan/tests/__init__.py
dpckan/tests/test_functions.py
dpckan-0.1.22.dist-info/LICENCE.txt
dpckan-0.1.22.dist-info/METADATA
dpckan-0.1.22.dist-info/WHEEL
dpckan-0.1.22.dist-info/entry_points.txt
dpckan-0.1.22.dist-info/top_level.txt
dpckan-0.1.22.dist-info/RECORD
