Metadata-Version: 2.1
Name: dpckan
Version: 0.1.22
Summary: Funções para gestão de pacotes de dados no portal dados.mg.gov.br
Home-page: https://github.com/dados-mg/dpkgckanmg
Author: CONTROLADORIA GERAL DO ESTADO DE MINAS GERAIS - CGE/MG
Author-email: dadosabertos@cge.mg.gov.br
License: UNKNOWN
Keywords: python,ckan
Platform: UNKNOWN
Classifier: Development Status :: 1 - Planning
Classifier: Intended Audience :: Developers
Classifier: Programming Language :: Python :: 3
Classifier: Operating System :: Unix
Classifier: Operating System :: MacOS :: MacOS X
Classifier: Operating System :: Microsoft :: Windows
License-File: LICENCE.txt
Requires-Dist: ckanapi ==4.0.0
Requires-Dist: click ==8.0.1
Requires-Dist: frictionless-ckan-mapper ==1.0.6
Requires-Dist: frictionless ==4.16.6
Requires-Dist: python-dotenv ==0.19.1
Requires-Dist: validators ==0.18.2
